simple_pyueye/__init__.py
simple_pyueye/camera.py
simple_pyueye/error_codes.py
simple_pyueye/ueye_codes.py
simple_pyueye_demo/__init__.py
simple_pyueye_demo/demos.py
simple_pyueye-0.0.7.dist-info/LICENSE
simple_pyueye-0.0.7.dist-info/METADATA
simple_pyueye-0.0.7.dist-info/WHEEL
simple_pyueye-0.0.7.dist-info/top_level.txt
simple_pyueye-0.0.7.dist-info/RECORD
