Metadata-Version: 2.1
Name: simple-pyueye
Version: 0.0.7
Summary: High-level wrapper for the python bindings package pyueye
Home-page: https://frontwave.pt/
Author: Joao Vital
Author-email: joao.vital@frontwave.com
License: 3-Clause BSD License
Platform: UNKNOWN
Requires-Dist: numpy
Requires-Dist: pillow
Requires-Dist: opencv-contrib-python
Requires-Dist: pyueye
Requires-Dist: pywin32
